odoo/addons/hr_attendance_validation/README.rst
odoo/addons/hr_attendance_validation/__init__.py
odoo/addons/hr_attendance_validation/__manifest__.py
odoo/addons/hr_attendance_validation/data/ir_cron.xml
odoo/addons/hr_attendance_validation/i18n/es.po
odoo/addons/hr_attendance_validation/i18n/fr.po
odoo/addons/hr_attendance_validation/i18n/hr_attendance_validation.pot
odoo/addons/hr_attendance_validation/i18n/it.po
odoo/addons/hr_attendance_validation/models/__init__.py
odoo/addons/hr_attendance_validation/models/hr_attendance.py
odoo/addons/hr_attendance_validation/models/hr_attendance_validation_sheet.py
odoo/addons/hr_attendance_validation/models/hr_employee.py
odoo/addons/hr_attendance_validation/models/hr_leave.py
odoo/addons/hr_attendance_validation/models/hr_leave_type.py
odoo/addons/hr_attendance_validation/models/res_config_settings.py
odoo/addons/hr_attendance_validation/models/resource_calendar.py
odoo/addons/hr_attendance_validation/readme/CONFIGURE.rst
odoo/addons/hr_attendance_validation/readme/CONTRIBUTORS.rst
odoo/addons/hr_attendance_validation/readme/DESCRIPTION.rst
odoo/addons/hr_attendance_validation/readme/ROADMAP.rst
odoo/addons/hr_attendance_validation/readme/USAGE.rst
odoo/addons/hr_attendance_validation/security/ir.model.access.csv
odoo/addons/hr_attendance_validation/security/ir.rule.xml
odoo/addons/hr_attendance_validation/static/description/icon.png
odoo/addons/hr_attendance_validation/static/description/index.html
odoo/addons/hr_attendance_validation/static/src/js/hr_attendance_validation.js
odoo/addons/hr_attendance_validation/static/src/xml/attendance.xml
odoo/addons/hr_attendance_validation/tests/__init__.py
odoo/addons/hr_attendance_validation/tests/test_hr_attendance_validation.py
odoo/addons/hr_attendance_validation/views/assets.xml
odoo/addons/hr_attendance_validation/views/hr_attendance.xml
odoo/addons/hr_attendance_validation/views/hr_attendance_validation.xml
odoo/addons/hr_attendance_validation/views/hr_leave_type.xml
odoo14_addon_hr_attendance_validation-14.0.1.1.0.dist-info/METADATA
odoo14_addon_hr_attendance_validation-14.0.1.1.0.dist-info/WHEEL
odoo14_addon_hr_attendance_validation-14.0.1.1.0.dist-info/top_level.txt
odoo14_addon_hr_attendance_validation-14.0.1.1.0.dist-info/RECORD
